setup.py
pdt_distributions/Binomialdistribution.py
pdt_distributions/Gaussiandistribution.py
pdt_distributions/Generaldistribution.py
pdt_distributions/__init__.py
pdt_distributions.egg-info/PKG-INFO
pdt_distributions.egg-info/SOURCES.txt
pdt_distributions.egg-info/dependency_links.txt
pdt_distributions.egg-info/not-zip-safe
pdt_distributions.egg-info/top_level.txt